fnb/__init__.py
fnb/backuper.py
fnb/cli.py
fnb/config.py
fnb/env.py
fnb/fetcher.py
fnb/gear.py
fnb/generator.py
fnb/logger.py
fnb/reader.py
fnb/assets/config.toml
fnb/assets/env.sample
fnb-0.12.1.dist-info/METADATA
fnb-0.12.1.dist-info/WHEEL
fnb-0.12.1.dist-info/entry_points.txt
fnb-0.12.1.dist-info/licenses/LICENSE
fnb-0.12.1.dist-info/RECORD
