Metadata-Version: 2.4
Name: fnb
Version: 0.12.1
Summary: Fetch'n'Backup - Simple two-step backup tool with rsync
Author-email: "Shota Takahashi (KMI)" <shotakaha@kmi.nagoya-u.ac.jp>
License: MIT
License-File: LICENSE
Keywords: backup,cli,fetch,rsync,sync
Classifier: Development Status :: 4 - Beta
Classifier: Environment :: Console
Classifier: Intended Audience :: System Administrators
Classifier: License :: OSI Approved :: MIT License
Classifier: Operating System :: OS Independent
Classifier: Programming Language :: Python :: 3
Classifier: Programming Language :: Python :: 3.12
Classifier: Topic :: System :: Archiving :: Backup
Classifier: Topic :: Utilities
Requires-Python: >=3.12
Requires-Dist: loguru>=0.7.0
Requires-Dist: pexpect>=4.9.0
Requires-Dist: platformdirs>=4.3.8
Requires-Dist: pydantic>=2.11.7
Requires-Dist: python-dotenv>=1.1.1
Requires-Dist: typer>=0.16.0
Provides-Extra: dev
Requires-Dist: commitizen>=4.8.3; extra == 'dev'
Requires-Dist: mkdocs-git-revision-date-localized-plugin>=1.4.7; extra == 'dev'
Requires-Dist: mkdocs-material[imaging]>=9.6.15; extra == 'dev'
Requires-Dist: mkdocs-static-i18n>=1.2.0; extra == 'dev'
Requires-Dist: mkdocstrings[python]>=0.30.0; extra == 'dev'
Requires-Dist: pip-audit>=2.7.3; extra == 'dev'
Requires-Dist: pre-commit>=4.2.0; extra == 'dev'
Requires-Dist: pytest-cov>=6.2.1; extra == 'dev'
Requires-Dist: pytest>=8.4.1; extra == 'dev'
Requires-Dist: ruff>=0.12.4; extra == 'dev'
Provides-Extra: docs
Requires-Dist: mkdocs-git-revision-date-localized-plugin>=1.4.7; extra == 'docs'
Requires-Dist: mkdocs-material[imaging]>=9.6.15; extra == 'docs'
Requires-Dist: mkdocs-static-i18n>=1.2.0; extra == 'docs'
Requires-Dist: mkdocstrings[python]>=0.30.0; extra == 'docs'
